ccr/__init__.py
ccr/utils.py
pyccr-0.0.22.dist-info/METADATA
pyccr-0.0.22.dist-info/WHEEL
pyccr-0.0.22.dist-info/top_level.txt
pyccr-0.0.22.dist-info/RECORD
